newsscraper/__init__.py
newsscraper/__main__.py
newsscraper/report.html
newsscraper-0.1.4.dist-info/LICENSE
newsscraper-0.1.4.dist-info/METADATA
newsscraper-0.1.4.dist-info/WHEEL
newsscraper-0.1.4.dist-info/top_level.txt
newsscraper-0.1.4.dist-info/RECORD
