Metadata-Version: 2.1
Name: newsscraper
Version: 0.1.4
Summary: News scraping and reporting.
Home-page: https://github.com/wichern/newsscraper
Author: Paul Wichern
Author-email: paul@menphis.de
License: MIT
Keywords: python3,webscraping,selenium,beautifulsoup4
Platform: UNKNOWN
Classifier: License :: OSI Approved :: MIT License
Classifier: Intended Audience :: Developers
Classifier: Programming Language :: Python :: 3
Classifier: Operating System :: OS Independent
Requires-Python: >=3.6
Requires-Dist: selenium
Requires-Dist: beautifulsoup4
